asgiref/__init__.py
asgiref/compatibility.py
asgiref/current_thread_executor.py
asgiref/local.py
asgiref/py.typed
asgiref/server.py
asgiref/sync.py
asgiref/testing.py
asgiref/timeout.py
asgiref/typing.py
asgiref/wsgi.py
asgiref-3.8.0.dist-info/LICENSE
asgiref-3.8.0.dist-info/METADATA
asgiref-3.8.0.dist-info/WHEEL
asgiref-3.8.0.dist-info/top_level.txt
asgiref-3.8.0.dist-info/RECORD
