Metadata-Version: 2.1
Name: asgiref
Version: 3.8.0
Summary: ASGI specs, helper code, and adapters
Home-page: https://github.com/django/asgiref/
Author: Django Software Foundation
Author-email: foundation@djangoproject.com
License: BSD-3-Clause
Project-URL: Documentation, https://asgi.readthedocs.io/
Project-URL: Further Documentation, https://docs.djangoproject.com/en/stable/topics/async/#async-adapter-functions
Project-URL: Changelog, https://github.com/django/asgiref/blob/master/CHANGELOG.txt
Classifier: Development Status :: 5 - Production/Stable
Classifier: Environment :: Web Environment
Classifier: Intended Audience :: Developers
Classifier: License :: OSI Approved :: BSD License
Classifier: Operating System :: OS Independent
Classifier: Programming Language :: Python
Classifier: Programming Language :: Python :: 3
Classifier: Programming Language :: Python :: 3 :: Only
Classifier: Programming Language :: Python :: 3.8
Classifier: Programming Language :: Python :: 3.9
Classifier: Programming Language :: Python :: 3.10
Classifier: Programming Language :: Python :: 3.11
Classifier: Programming Language :: Python :: 3.12
Classifier: Topic :: Internet :: WWW/HTTP
Requires-Python: >=3.8
License-File: LICENSE
Requires-Dist: typing_extensions>=4; python_version < "3.11"
Provides-Extra: tests
Requires-Dist: pytest; extra == "tests"
Requires-Dist: pytest-asyncio; extra == "tests"
Requires-Dist: mypy>=0.800; extra == "tests"
